Workbook

Sheet Інструкція
A1: Юніт-економіка Verivo — юніт = автомобіль (VIN)
A3: ЩО ЦЕ | B3: Модель економіки ОДНОГО автомобіля з живою історією за горизонт 8 років. Не помісячний кеш-флоу компанії — саме юніт.
A4: ЮНІТ | B4: Автомобіль (VIN). Історія належить авто і переживає власників (рішення засновника 19.08.2026). LTV рахується на авто, CAC — вартість «посадити» одне авто.
A5: ГОЛОВНА МЕТРИКА | B5: Continuity rate — частка історій, що переживають зміну власника. Змініть її на аркуші «Припущення» і подивіться на Підсумки: різниця = гроші, які живуть у безперервності.
A6: АРКУШ «Припущення» | B6: Єдине місце вводу. Жовта заливка + синій текст = можна міняти. ВСІ значення — припущення для калібрування, НЕ прогноз. [TBD] = перевіряється тестами з VC-003.
A7: АРКУШ «Юніт-модель» | B7: Розрахунок доходів/витрат одного авто по роках 1–8. Нічого не міняти — все формули.
A8: АРКУШ «Підсумки» | B8: LTV авто, LTV/CAC, розбивка за потоками і ціна continuity.
A9: ЧОГО ТУТ НЕМАЄ | B9: Дисконтування, податків, валютних курсів, помісячної каси. Свідомо: спершу перевіряємо, чи юніт взагалі заробляє.

Sheet Припущення
A1: Припущення (вхідні дані юніта)
A2: Міняйте тільки жовті клітинки. Кожне число — припущення (≈) або [TBD] до перевірки тестами.
A4: Юніт і час
A5: Горизонт моделі, років | B5: 8 | C5: ≈2 цикли володіння. Досить, щоб побачити ефект continuity.
A6: Середній цикл володіння, років | B6: 4 | C6: ≈ припущення. UA-статистики під рукою немає — [TBD].
A7: Continuity rate (0…1) | B7: 0.5 | C7: Частка історій, що переживають зміну власника. ГОЛОВНИЙ ВАЖІЛЬ. 0 = історія вмирає з власником; 1 = завжди передається. [TBD — це продуктова гіпотеза].
A9: Потік 1 — Verified-записи (платить СТО)
A10: Сервісних подій на 1 авто/рік | B10: 3 | C10: ≈ ТО + сезонна зміна шин + дрібний ремонт.
A11: Частка подій, що стають verified-записами (0…1) | B11: 0.5 | C11: Залежить від покриття СТО. [TBD — UK СТО-тест].
A12: Ціна для СТО за 1 verified-запис, € | B12: 1 | C12: [TBD — UK СТО-тест]. Для СТО це брендоване підтвердження роботи, що лишається з авто.
A14: Потік 2 — Момент угоди
A15: Attach rate платного продукту угоди (0…1) | B15: 0.2 | C15: Частка продажів авто, де хтось платить за живе джерело/пакет. [TBD — Sale Pack-тест]. Після скріншот-аргументу: платять лише за незалежне живе джерело.
A16: Ціна продукту угоди, € | B16: 25 | C16: Орієнтир ринку звітів: CarFax ≈$45, carVertical ≈€30 (перевірити). [TBD]
A18: Потік 3 — Власник (за замовч. вимкнено)
A19: Підписка власника, €/міс | B19: 0 | C19: Стара модель B (₴79–99 ≈ €1.5–2). Залишено як важіль: постав значення — побачиш внесок підписки.
A21: Витрати юніта
A22: CAC: залучення 1 авто, € | B22: 3 | C22: ≈ вартість встановлення+активації на 1 авто. [TBD]
A23: Інфраструктура + AI на 1 авто/рік, € | B23: 0.5 | C23: ≈ сховище, розпізнавання чеків.
A24: CAC 1 СТО (разово), € | B24: 200 | C24: ≈ прямий продаж/онбординг одного СТО. [TBD — UK-тест]
A25: Verified-записів від 1 СТО/рік | B25: 300 | C25: ≈ 25/міс. [TBD]
A26: Строк співпраці зі СТО, років | B26: 3 | C26: ≈ припущення.
A27: Амортизація CAC СТО на 1 запис, € | B27: =B24/(B25*B26) -> 0.22222222 | C27: Формула: CAC СТО ÷ (записів/рік × строк). Не міняти.

Sheet Юніт-модель
A1: Економіка одного автомобіля по роках
A2: Все формули. «Історія жива» = continuity^(кількість пройдених змін власника).
A4: Рік | B4: Історія жива, ймовірність | C4: Дохід: verified-записи, € | D4: Дохід: момент угоди, € | E4: Дохід: підписка власника, € | F4: ДОХІД РАЗОМ, € | G4: Витрати: інфра+AI, € | H4: Витрати: аморт. CAC СТО, € | I4: ВИТРАТИ РАЗОМ, € | J4: Нетто за рік, € | K4: Кумулятивно (з CAC авто), €
A5: 1 | B5: =Припущення!$B$7^FLOOR((A5-1)/Припущення!$B$6,1) -> 1 | C5: =B5*Припущення!$B$10*Припущення!$B$11*Припущення!$B$12 -> 1.5 | D5: =B5*(1/Припущення!$B$6)*Припущення!$B$15*Припущення!$B$16 -> 1.25 | E5: =B5*Припущення!$B$19*12 -> 0 | F5: =SUM(C5:E5) -> 2.75 | G5: =B5*Припущення!$B$23 -> 0.5 | H5: =B5*Припущення!$B$10*Припущення!$B$11*Припущення!$B$27 -> 0.33333333 | I5: =SUM(G5:H5) -> 0.83333333 | J5: =F5-I5 -> 1.9166667 | K5: =J5-Припущення!$B$22 -> -1.0833333
A6: 2 | B6: =Припущення!$B$7^FLOOR((A6-1)/Припущення!$B$6,1) -> 1 | C6: =B6*Припущення!$B$10*Припущення!$B$11*Припущення!$B$12 -> 1.5 | D6: =B6*(1/Припущення!$B$6)*Припущення!$B$15*Припущення!$B$16 -> 1.25 | E6: =B6*Припущення!$B$19*12 -> 0 | F6: =SUM(C6:E6) -> 2.75 | G6: =B6*Припущення!$B$23 -> 0.5 | H6: =B6*Припущення!$B$10*Припущення!$B$11*Припущення!$B$27 -> 0.33333333 | I6: =SUM(G6:H6) -> 0.83333333 | J6: =F6-I6 -> 1.9166667 | K6: =K5+J6 -> 0.83333333
A7: 3 | B7: =Припущення!$B$7^FLOOR((A7-1)/Припущення!$B$6,1) -> 1 | C7: =B7*Припущення!$B$10*Припущення!$B$11*Припущення!$B$12 -> 1.5 | D7: =B7*(1/Припущення!$B$6)*Припущення!$B$15*Припущення!$B$16 -> 1.25 | E7: =B7*Припущення!$B$19*12 -> 0 | F7: =SUM(C7:E7) -> 2.75 | G7: =B7*Припущення!$B$23 -> 0.5 | H7: =B7*Припущення!$B$10*Припущення!$B$11*Припущення!$B$27 -> 0.33333333 | I7: =SUM(G7:H7) -> 0.83333333 | J7: =F7-I7 -> 1.9166667 | K7: =K6+J7 -> 2.75
A8: 4 | B8: =Припущення!$B$7^FLOOR((A8-1)/Припущення!$B$6,1) -> 1 | C8: =B8*Припущення!$B$10*Припущення!$B$11*Припущення!$B$12 -> 1.5 | D8: =B8*(1/Припущення!$B$6)*Припущення!$B$15*Припущення!$B$16 -> 1.25 | E8: =B8*Припущення!$B$19*12 -> 0 | F8: =SUM(C8:E8) -> 2.75 | G8: =B8*Припущення!$B$23 -> 0.5 | H8: =B8*Припущення!$B$10*Припущення!$B$11*Припущення!$B$27 -> 0.33333333 | I8: =SUM(G8:H8) -> 0.83333333 | J8: =F8-I8 -> 1.9166667 | K8: =K7+J8 -> 4.6666667
A9: 5 | B9: =Припущення!$B$7^FLOOR((A9-1)/Припущення!$B$6,1) -> 0.5 | C9: =B9*Припущення!$B$10*Припущення!$B$11*Припущення!$B$12 -> 0.75 | D9: =B9*(1/Припущення!$B$6)*Припущення!$B$15*Припущення!$B$16 -> 0.625 | E9: =B9*Припущення!$B$19*12 -> 0 | F9: =SUM(C9:E9) -> 1.375 | G9: =B9*Припущення!$B$23 -> 0.25 | H9: =B9*Припущення!$B$10*Припущення!$B$11*Припущення!$B$27 -> 0.16666667 | I9: =SUM(G9:H9) -> 0.41666667 | J9: =F9-I9 -> 0.95833333 | K9: =K8+J9 -> 5.625
A10: 6 | B10: =Припущення!$B$7^FLOOR((A10-1)/Припущення!$B$6,1) -> 0.5 | C10: =B10*Припущення!$B$10*Припущення!$B$11*Припущення!$B$12 -> 0.75 | D10: =B10*(1/Припущення!$B$6)*Припущення!$B$15*Припущення!$B$16 -> 0.625 | E10: =B10*Припущення!$B$19*12 -> 0 | F10: =SUM(C10:E10) -> 1.375 | G10: =B10*Припущення!$B$23 -> 0.25 | H10: =B10*Припущення!$B$10*Припущення!$B$11*Припущення!$B$27 -> 0.16666667 | I10: =SUM(G10:H10) -> 0.41666667 | J10: =F10-I10 -> 0.95833333 | K10: =K9+J10 -> 6.5833333
A11: 7 | B11: =Припущення!$B$7^FLOOR((A11-1)/Припущення!$B$6,1) -> 0.5 | C11: =B11*Припущення!$B$10*Припущення!$B$11*Припущення!$B$12 -> 0.75 | D11: =B11*(1/Припущення!$B$6)*Припущення!$B$15*Припущення!$B$16 -> 0.625 | E11: =B11*Припущення!$B$19*12 -> 0 | F11: =SUM(C11:E11) -> 1.375 | G11: =B11*Припущення!$B$23 -> 0.25 | H11: =B11*Припущення!$B$10*Припущення!$B$11*Припущення!$B$27 -> 0.16666667 | I11: =SUM(G11:H11) -> 0.41666667 | J11: =F11-I11 -> 0.95833333 | K11: =K10+J11 -> 7.5416667
A12: 8 | B12: =Припущення!$B$7^FLOOR((A12-1)/Припущення!$B$6,1) -> 0.5 | C12: =B12*Припущення!$B$10*Припущення!$B$11*Припущення!$B$12 -> 0.75 | D12: =B12*(1/Припущення!$B$6)*Припущення!$B$15*Припущення!$B$16 -> 0.625 | E12: =B12*Припущення!$B$19*12 -> 0 | F12: =SUM(C12:E12) -> 1.375 | G12: =B12*Припущення!$B$23 -> 0.25 | H12: =B12*Припущення!$B$10*Припущення!$B$11*Припущення!$B$27 -> 0.16666667 | I12: =SUM(G12:H12) -> 0.41666667 | J12: =F12-I12 -> 0.95833333 | K12: =K11+J12 -> 8.5

Sheet Підсумки
A1: Підсумки юніта (1 автомобіль, горизонт 8 років)
A3: LTV авто (дохід за горизонт), € | B3: =SUM('Юніт-модель'!F5:F12) -> 16.5
A4: — з нього verified-записи, € | B4: =SUM('Юніт-модель'!C5:C12) -> 9
A5: — з нього момент угоди, € | B5: =SUM('Юніт-модель'!D5:D12) -> 7.5
A6: — з нього підписка, € | B6: =SUM('Юніт-модель'!E5:E12) -> 0
A8: Витрати юніта за горизонт (без CAC), € | B8: =SUM('Юніт-модель'!I5:I12) -> 5
A9: CAC авто, € | B9: =Припущення!B22 -> 3
A10: Нетто юніта за горизонт (після CAC), € | B10: =SUM('Юніт-модель'!J5:J12)-Припущення!B22 -> 8.5
A11: LTV/CAC (нетто до CAC ÷ CAC) | B11: =SUM('Юніт-модель'!J5:J12)/Припущення!B22 -> 3.8333333 | C11: Здорове SaaS-правило великого пальця: >3x. Тут — лише калібрування, не прогноз.
A13: Ціна безперервності (continuity)
A14: Дохід лише за 1-й цикл володіння, € | B14: =SUMPRODUCT(('Юніт-модель'!A5:A12<=Припущення!B6)*'Юніт-модель'!F5:F12) -> 11 | C14: Це вся виручка юніта, якщо історія ВМИРАЄ з власником (continuity = 0).
A15: Дохід, що живе в continuity, € | B15: =SUM('Юніт-модель'!F5:F12)-SUMPRODUCT(('Юніт-модель'!A5:A12<=Припущення!B6)*'Юніт-модель'!F5:F12) -> 5.5 | C15: Різниця = гроші, які існують лише якщо історія переживає зміну власника. Це грошовий вираз головної метрики продукту.
A16: Частка LTV, залежна від continuity | B16: =B15/B3 -> 0.33333333
A18: Нагадування
A19: Всі вхідні — припущення (≈) або [TBD]; перевіряються тестами з VC-003: Sale Pack-тест → attach rate і ціна угоди; UK СТО-тест → ціна за запис і частка verified. Модель без дисконтування і податків.
